{
  "video_hash": "35a36172fa88d9daeac785668e00159a",
  "video_metadata": {
    "filename": "cam3.avi",
    "width": 720,
    "height": 480,
    "fps": 24,
    "total_frames": 126,
    "color_mode": "BGR",
    "total_duration_seconds": 5.25,
    "camera_angle": "body_level",
    "environment": "living_room",
    "video_quality": "good",
    "number_of_person": 1
  },
  "persons": [
    {
      "person_id": 1,
      "yolo_track_id": 13479,
      "main_subject_age_group": "young",
      "person_mobility": "normal",
      "keypoints_sequence": [
        {
          "frame_num": 0,
          "keypoints": null,
          "bbox": null,
          "bbox_confidence": null
        },
        {
          "frame_num": 1,
          "keypoints": null,
          "bbox": null,
          "bbox_confidence": null
        },
        {
          "frame_num": 2,
          "keypoints": null,
          "bbox": null,
          "bbox_confidence": null
        },
        {
          "frame_num": 3,
          "keypoints": null,
          "bbox": null,
          "bbox_confidence": null
        },
        {
          "frame_num": 4,
          "keypoints": null,
          "bbox": null,
          "bbox_confidence": null
        },
        {
          "frame_num": 5,
          "keypoints": null,
          "bbox": null,
          "bbox_confidence": null
        },
        {
          "frame_num": 6,
          "keypoints": null,
          "bbox": null,
          "bbox_confidence": null
        },
        {
          "frame_num": 7,
          "keypoints": null,
          "bbox": null,
          "bbox_confidence": null
        },
        {
          "frame_num": 8,
          "keypoints": null,
          "bbox": null,
          "bbox_confidence": null
        },
        {
          "frame_num": 9,
          "keypoints": null,
          "bbox": null,
          "bbox_confidence": null
        },
        {
          "frame_num": 10,
          "keypoints": null,
          "bbox": null,
          "bbox_confidence": null
        },
        {
          "frame_num": 11,
          "keypoints": null,
          "bbox": null,
          "bbox_confidence": null
        },
        {
          "frame_num": 12,
          "keypoints": null,
          "bbox": null,
          "bbox_confidence": null
        },
        {
          "frame_num": 13,
          "keypoints": null,
          "bbox": null,
          "bbox_confidence": null
        },
        {
          "frame_num": 14,
          "keypoints": null,
          "bbox": null,
          "bbox_confidence": null
        },
        {
          "frame_num": 15,
          "keypoints": null,
          "bbox": null,
          "bbox_confidence": null
        },
        {
          "frame_num": 16,
          "keypoints": null,
          "bbox": null,
          "bbox_confidence": null
        },
        {
          "frame_num": 17,
          "keypoints": null,
          "bbox": null,
          "bbox_confidence": null
        },
        {
          "frame_num": 18,
          "keypoints": null,
          "bbox": null,
          "bbox_confidence": null
        },
        {
          "frame_num": 19,
          "keypoints": null,
          "bbox": null,
          "bbox_confidence": null
        },
        {
          "frame_num": 20,
          "keypoints": null,
          "bbox": null,
          "bbox_confidence": null
        },
        {
          "frame_num": 21,
          "keypoints": null,
          "bbox": null,
          "bbox_confidence": null
        },
        {
          "frame_num": 22,
          "keypoints": null,
          "bbox": null,
          "bbox_confidence": null
        },
        {
          "frame_num": 23,
          "keypoints": null,
          "bbox": null,
          "bbox_confidence": null
        },
        {
          "frame_num": 24,
          "keypoints": null,
          "bbox": null,
          "bbox_confidence": null
        },
        {
          "frame_num": 25,
          "keypoints": null,
          "bbox": null,
          "bbox_confidence": null
        },
        {
          "frame_num": 26,
          "keypoints": [
            [
              37.04844284057617,
              335.79766845703125,
              0.0774560272693634
            ],
            [
              33.578556060791016,
              330.7253112792969,
              0.016196686774492264
            ],
            [
              33.83734130859375,
              332.3299255371094,
              0.08260013163089752
            ],
            [
              14.295400619506836,
              331.2334289550781,
              0.021413374692201614
            ],
            [
              22.123916625976562,
              336.76422119140625,
              0.230721116065979
            ],
            [
              13.73878288269043,
              353.60943603515625,
              0.23061759769916534
            ],
            [
              14.432193756103516,
              364.4346008300781,
              0.8270970582962036
            ],
            [
              17.22956657409668,
              377.7242126464844,
              0.12607474625110626
            ],
            [
              13.659116744995117,
              403.6671447753906,
              0.9159412980079651
            ],
            [
              44.858154296875,
              378.4509582519531,
              0.2896277904510498
            ],
            [
              51.60559844970703,
              422.5901184082031,
              0.8947356343269348
            ],
            [
              26.662389755249023,
              394.1164245605469,
              0.6482158303260803
            ],
            [
              25.18797492980957,
              403.3975830078125,
              0.8815608024597168
            ],
            [
              74.78665924072266,
              412.11932373046875,
              0.7816199064254761
            ],
            [
              73.44180297851562,
              426.7922668457031,
              0.9573475122451782
            ],
            [
              88.2056884765625,
              454.2878723144531,
              0.7566961050033569
            ],
            [
              79.14703369140625,
              466.3421630859375,
              0.9228980541229248
            ]
          ],
          "bbox": [
            0.3943618834018707,
            335.26947021484375,
            113.27287292480469,
            142.13052368164062
          ],
          "bbox_confidence": 0.7600789070129395
        },
        {
          "frame_num": 27,
          "keypoints": [
            [
              20.63182258605957,
              307.3849182128906,
              0.02360205166041851
            ],
            [
              19.273164749145508,
              303.8013610839844,
              0.007686985190957785
            ],
            [
              18.074316024780273,
              304.1454772949219,
              0.015245964750647545
            ],
            [
              9.623053550720215,
              305.8265075683594,
              0.019027628004550934
            ],
            [
              11.763614654541016,
              308.20172119140625,
              0.053828462958335876
            ],
            [
              10.90762996673584,
              321.18975830078125,
              0.21577906608581543
            ],
            [
              9.031903266906738,
              330.775634765625,
              0.22778622806072235
            ],
            [
              29.759933471679688,
              334.9819030761719,
              0.3116772174835205
            ],
            [
              27.43233871459961,
              361.3233947753906,
              0.39754223823547363
            ],
            [
              41.615478515625,
              316.6910400390625,
              0.41334089636802673
            ],
            [
              38.03580093383789,
              330.5434875488281,
              0.5070783495903015
            ],
            [
              35.47737121582031,
              373.26287841796875,
              0.8153446316719055
            ],
            [
              32.59197235107422,
              381.218505859375,
              0.812538206577301
            ],
            [
              93.57992553710938,
              392.528564453125,
              0.9178003668785095
            ],
            [
              91.39048767089844,
              395.67791748046875,
              0.9426013231277466
            ],
            [
              116.62454223632812,
              425.39349365234375,
              0.8843539357185364
            ],
            [
              116.17889404296875,
              429.7757873535156,
              0.9120154976844788
            ]
          ],
          "bbox": [
            1.2769917249679565,
            308.9374084472656,
            140.4161834716797,
            146.31613159179688
          ],
          "bbox_confidence": 0.5783597826957703
        },
        {
          "frame_num": 28,
          "keypoints": [
            [
              30.644073486328125,
              265.1833190917969,
              0.970753014087677
            ],
            [
              27.97223472595215,
              260.9202880859375,
              0.5600400567054749
            ],
            [
              21.758384704589844,
              263.85186767578125,
              0.9684657454490662
            ],
            [
              24.739439010620117,
              266.37420654296875,
              0.014345037750899792
            ],
            [
              7.786079406738281,
              275.760986328125,
              0.891462504863739
            ],
            [
              26.840877532958984,
              286.12945556640625,
              0.9765346050262451
            ],
            [
              15.31765365600586,
              310.31634521484375,
              0.9765946269035339
            ],
            [
              44.60235595703125,
              300.055908203125,
              0.9223788976669312
            ],
            [
              47.642520904541016,
              356.16851806640625,
              0.9486070275306702
            ],
            [
              61.954429626464844,
              304.50677490234375,
              0.9549185633659363
            ],
            [
              87.75019073486328,
              383.24127197265625,
              0.9649854898452759
            ],
            [
              65.07862854003906,
              346.78692626953125,
              0.9894513487815857
            ],
            [
              51.46137619018555,
              363.3533935546875,
              0.9897391200065613
            ],
            [
              106.46339416503906,
              372.2621154785156,
              0.9954453706741333
            ],
            [
              73.43914031982422,
              399.375732421875,
              0.9968225955963135
            ],
            [
              141.9813232421875,
              397.7115783691406,
              0.9880576133728027
            ],
            [
              92.33209228515625,
              437.9974670410156,
              0.9890298247337341
            ]
          ],
          "bbox": [
            0.9420533180236816,
            257.21575927734375,
            163.4306182861328,
            199.54205322265625
          ],
          "bbox_confidence": 0.9272623658180237
        },
        {
          "frame_num": 29,
          "keypoints": [
            [
              55.357486724853516,
              244.4217529296875,
              0.8765929341316223
            ],
            [
              52.56170654296875,
              239.18399047851562,
              0.31253665685653687
            ],
            [
              48.63554763793945,
              241.57901000976562,
              0.9264642000198364
            ],
            [
              41.58961486816406,
              242.58714294433594,
              0.06619776040315628
            ],
            [
              35.37439727783203,
              249.58145141601562,
              0.968023955821991
            ],
            [
              40.409786224365234,
              266.2893981933594,
              0.9377362728118896
            ],
            [
              48.700347900390625,
              280.9387512207031,
              0.9953027963638306
            ],
            [
              60.650474548339844,
              290.3873596191406,
              0.2860839366912842
            ],
            [
              77.51329803466797,
              325.6090087890625,
              0.9663981199264526
            ],
            [
              83.21569061279297,
              308.0986328125,
              0.26198139786720276
            ],
            [
              122.26533508300781,
              346.8961181640625,
              0.8923861384391785
            ],
            [
              61.9128303527832,
              324.8438415527344,
              0.9680315256118774
            ],
            [
              65.843017578125,
              333.74468994140625,
              0.9917388558387756
            ],
            [
              106.53093719482422,
              352.62847900390625,
              0.9821350574493408
            ],
            [
              106.07652282714844,
              358.6040954589844,
              0.9972954392433167
            ],
            [
              121.93209838867188,
              397.8804016113281,
              0.9796434044837952
            ],
            [
              122.37479400634766,
              403.9216003417969,
              0.9949548840522766
            ]
          ],
          "bbox": [
            7.157905578613281,
            223.09115600585938,
            167.90655517578125,
            215.09902954101562
          ],
          "bbox_confidence": 0.9132760167121887
        },
        {
          "frame_num": 30,
          "keypoints": [
            [
              75.90023803710938,
              219.49888610839844,
              0.9567757844924927
            ],
            [
              72.21644592285156,
              214.28163146972656,
              0.24679140746593475
            ],
            [
              67.67784881591797,
              217.4664306640625,
              0.9822868704795837
            ],
            [
              55.198333740234375,
              218.00418090820312,
              0.013675205409526825
            ],
            [
              52.71943664550781,
              228.5287628173828,
              0.992878258228302
            ],
            [
              48.58412170410156,
              242.08140563964844,
              0.9209455251693726
            ],
            [
              68.9825210571289,
              264.149658203125,
              0.99847811460495
            ],
            [
              80.44573974609375,
              264.36083984375,
              0.14031627774238586
            ],
            [
              106.97854614257812,
              300.2053527832031,
              0.9922938346862793
            ],
            [
              103.95696258544922,
              276.0257873535156,
              0.17383776605129242
            ],
            [
              147.5685272216797,
              302.99285888671875,
              0.9690520763397217
            ],
            [
              78.19038391113281,
              301.8455505371094,
              0.916744589805603
            ],
            [
              92.24726104736328,
              316.26318359375,
              0.9878095388412476
            ],
            [
              118.34309387207031,
              320.1986999511719,
              0.8497768044471741
            ],
            [
              131.6988983154297,
              343.1738586425781,
              0.986368715763092
            ],
            [
              131.13792419433594,
              366.8478698730469,
              0.738462507724762
            ],
            [
              137.64820861816406,
              389.7338562011719,
              0.9438639879226685
            ]
          ],
          "bbox": [
            21.344104766845703,
            191.63958740234375,
            157.244384765625,
            220.40679931640625
          ],
          "bbox_confidence": 0.9045683741569519
        },
        {
          "frame_num": 31,
          "keypoints": [
            [
              94.71704864501953,
              202.1265106201172,
              0.8602965474128723
            ],
            [
              89.81180572509766,
              199.45069885253906,
              0.12778763473033905
            ],
            [
              87.49816131591797,
              199.7190704345703,
              0.9225596785545349
            ],
            [
              70.37389373779297,
              207.35813903808594,
              0.021258758381009102
            ],
            [
              73.93058013916016,
              211.17990112304688,
              0.985721230506897
            ],
            [
              68.3472671508789,
              230.2569122314453,
              0.9377328157424927
            ],
            [
              90.5112075805664,
              245.91905212402344,
              0.9978199005126953
            ],
            [
              102.00923919677734,
              245.9669647216797,
              0.22941717505455017
            ],
            [
              127.6060791015625,
              281.1334228515625,
              0.9882161021232605
            ],
            [
              127.50540161132812,
              254.58042907714844,
              0.2040523737668991
            ],
            [
              163.92831420898438,
              279.513427734375,
              0.948542058467865
            ],
            [
              95.05644226074219,
              288.665283203125,
              0.9695999026298523
            ],
            [
              108.04402923583984,
              300.34552001953125,
              0.9945197701454163
            ],
            [
              132.74411010742188,
              308.256103515625,
              0.9604998230934143
            ],
            [
              137.5261993408203,
              334.83026123046875,
              0.9958789348602295
            ],
            [
              160.6835479736328,
              336.37335205078125,
              0.9414105415344238
            ],
            [
              151.73062133789062,
              375.0523376464844,
              0.9870201349258423
            ]
          ],
          "bbox": [
            40.92097473144531,
            174.531982421875,
            147.63897705078125,
            226.77450561523438
          ],
          "bbox_confidence": 0.9115093946456909
        },
        {
          "frame_num": 32,
          "keypoints": [
            [
              115.28011322021484,
              181.84503173828125,
              0.8788387179374695
            ],
            [
              109.8053970336914,
              179.77822875976562,
              0.09721355885267258
            ],
            [
              107.33882141113281,
              179.55201721191406,
              0.9392471313476562
            ],
            [
              89.32899475097656,
              189.6387939453125,
              0.012984324246644974
            ],
            [
              93.7026138305664,
              192.21112060546875,
              0.992425799369812
            ],
            [
              83.81221771240234,
              214.24176025390625,
              0.9493516683578491
            ],
            [
              113.45883178710938,
              224.65516662597656,
              0.9986807703971863
            ],
            [
              103.94727325439453,
              241.58042907714844,
              0.1957879364490509
            ],
            [
              142.49649047851562,
              265.17730712890625,
              0.9890636801719666
            ],
            [
              133.4759521484375,
              254.8848876953125,
              0.1501685231924057
            ],
            [
              177.48167419433594,
              275.7945556640625,
              0.9411741495132446
            ],
            [
              110.94076538085938,
              271.69635009765625,
              0.9685105681419373
            ],
            [
              126.64894104003906,
              281.13543701171875,
              0.9951968789100647
            ],
            [
              152.521728515625,
              298.8659973144531,
              0.9723027348518372
            ],
            [
              152.73095703125,
              324.3110046386719,
              0.997680127620697
            ],
            [
              173.07672119140625,
              331.5503234863281,
              0.9641753435134888
            ],
            [
              145.6573028564453,
              374.7382507324219,
              0.9933103322982788
            ]
          ],
          "bbox": [
            62.51139450073242,
            153.8219451904297,
            135.8489532470703,
            237.95790100097656
          ],
          "bbox_confidence": 0.9285867810249329
        },
        {
          "frame_num": 33,
          "keypoints": [
            [
              133.1254425048828,
              162.09397888183594,
              0.6218541860580444
            ],
            [
              128.7150421142578,
              160.26856994628906,
              0.05038239434361458
            ],
            [
              127.51996612548828,
              159.65505981445312,
              0.749104380607605
            ],
            [
              106.12809753417969,
              169.62384033203125,
              0.03700370714068413
            ],
            [
              116.19071197509766,
              171.37918090820312,
              0.979619026184082
            ],
            [
              99.49596405029297,
              190.81509399414062,
              0.9588708877563477
            ],
            [
              131.67095947265625,
              204.80853271484375,
              0.9984885454177856
            ],
            [
              116.7741470336914,
              199.8007049560547,
              0.2555859088897705
            ],
            [
              154.02886962890625,
              249.63487243652344,
              0.990896999835968
            ],
            [
              138.12576293945312,
              199.706787109375,
              0.1764819175004959
            ],
            [
              178.5543212890625,
              270.611083984375,
              0.9383994340896606
            ],
            [
              124.85334777832031,
              255.67318725585938,
              0.9816300868988037
            ],
            [
              144.64215087890625,
              263.2489013671875,
              0.9966034889221191
            ],
            [
              167.4521942138672,
              286.50433349609375,
              0.9725351929664612
            ],
            [
              180.14096069335938,
              295.0885925292969,
              0.9972706437110901
            ],
            [
              172.09864807128906,
              326.5735168457031,
              0.9459662437438965
            ],
            [
              174.21554565429688,
              336.2021484375,
              0.9899817109107971
            ]
          ],
          "bbox": [
            77.19774627685547,
            138.6461181640625,
            124.3572769165039,
            229.31298828125
          ],
          "bbox_confidence": 0.9132906198501587
        },
        {
          "frame_num": 34,
          "keypoints": [
            [
              153.8806610107422,
              152.9206085205078,
              0.4620879590511322
            ],
            [
              150.25787353515625,
              150.17401123046875,
              0.02145516313612461
            ],
            [
              149.62486267089844,
              149.26942443847656,
              0.5920087695121765
            ],
            [
              126.10484313964844,
              157.57850646972656,
              0.03766729682683945
            ],
            [
              138.94110107421875,
              157.62844848632812,
              0.9869339466094971
            ],
            [
              115.3022689819336,
              181.59246826171875,
              0.9773691296577454
            ],
            [
              152.734130859375,
              188.1761474609375,
              0.9990291595458984
            ],
            [
              119.73641967773438,
              201.36569213867188,
              0.32894599437713623
            ],
            [
              168.91233825683594,
              236.2067108154297,
              0.9903918504714966
            ],
            [
              140.0372772216797,
              220.3439483642578,
              0.147384375333786
            ],
            [
              191.36102294921875,
              261.9748840332031,
              0.914929211139679
            ],
            [
              135.5336456298828,
              241.34596252441406,
              0.9908133149147034
            ],
            [
              161.5260772705078,
              243.93402099609375,
              0.9979878664016724
            ],
            [
              159.80325317382812,
              279.76446533203125,
              0.9896518588066101
            ],
            [
              193.93182373046875,
              272.4216003417969,
              0.9984667897224426
            ],
            [
              175.09828186035156,
              322.2237854003906,
              0.9786722660064697
            ],
            [
              203.87644958496094,
              313.3581237792969,
              0.9951275587081909
            ]
          ],
          "bbox": [
            101.60541534423828,
            125.0984878540039,
            123.61347198486328,
            221.54052734375
          ],
          "bbox_confidence": 0.928662896156311
        },
        {
          "frame_num": 35,
          "keypoints": [
            [
              176.21914672851562,
              143.4135284423828,
              0.5320749282836914
            ],
            [
              173.1884765625,
              139.61256408691406,
              0.031464122235774994
            ],
            [
              173.5161590576172,
              139.85057067871094,
              0.6534132361412048
            ],
            [
              150.18011474609375,
              144.90650939941406,
              0.050820305943489075
            ],
            [
              163.84336853027344,
              146.50637817382812,
              0.9874414205551147
            ],
            [
              138.0933837890625,
              170.59983825683594,
              0.9804546236991882
            ],
            [
              173.6685791015625,
              179.3740997314453,
              0.9991176724433899
            ],
            [
              138.59976196289062,
              194.95916748046875,
              0.34920257329940796
            ],
            [
              191.12481689453125,
              224.38742065429688,
              0.9873443841934204
            ],
            [
              158.23007202148438,
              218.63223266601562,
              0.16600362956523895
            ],
            [
              212.0403594970703,
              249.7741241455078,
              0.8942855596542358
            ],
            [
              154.08279418945312,
              232.30471801757812,
              0.9908573031425476
            ],
            [
              179.39605712890625,
              235.17529296875,
              0.997701108455658
            ],
            [
              168.62403869628906,
              276.5892333984375,
              0.9911735653877258
            ],
            [
              206.79486083984375,
              266.0604248046875,
              0.9980068802833557
            ],
            [
              180.65625,
              322.1339416503906,
              0.9814404249191284
            ],
            [
              225.27383422851562,
              292.10247802734375,
              0.9944867491722107
            ]
          ],
          "bbox": [
            124.65894317626953,
            114.69621276855469,
            123.2999038696289,
            222.79090881347656
          ],
          "bbox_confidence": 0.9194301962852478
        },
        {
          "frame_num": 36,
          "keypoints": [
            [
              197.4027862548828,
              132.07455444335938,
              0.32574376463890076
            ],
            [
              194.11277770996094,
              127.07991027832031,
              0.012745464220643044
            ],
            [
              195.29298400878906,
              127.74360656738281,
              0.46693485975265503
            ],
            [
              170.23292541503906,
              129.7042236328125,
              0.04557383805513382
            ],
            [
              186.22225952148438,
              131.8573455810547,
              0.9860185384750366
            ],
            [
              158.71127319335938,
              155.13577270507812,
              0.9794315695762634
            ],
            [
              195.2528839111328,
              164.49078369140625,
              0.9994589686393738
            ],
            [
              161.106689453125,
              178.5543670654297,
              0.24823875725269318
            ],
            [
              214.0706329345703,
              203.3234405517578,
              0.9922316074371338
            ],
            [
              181.04623413085938,
              199.82742309570312,
              0.10293620079755783
            ],
            [
              233.7242431640625,
              223.03964233398438,
              0.9080303907394409
            ],
            [
              173.86767578125,
              213.0570831298828,
              0.9947980642318726
            ],
            [
              199.85069274902344,
              217.5883026123047,
              0.9990997314453125
            ],
            [
              193.1071014404297,
              248.71322631835938,
              0.9944668412208557
            ],
            [
              221.54127502441406,
              248.54443359375,
              0.9992885589599609
            ],
            [
              186.6801300048828,
              295.7495422363281,
              0.9902094602584839
            ],
            [
              234.22628784179688,
              288.1116943359375,
              0.9978910088539124
            ]
          ],
          "bbox": [
            144.91079711914062,
            101.95430755615234,
            113.7779541015625,
            217.54998779296875
          ],
          "bbox_confidence": 0.9274367690086365
        },
        {
          "frame_num": 37,
          "keypoints": [
            [
              214.15316772460938,
              122.318359375,
              0.33401644229888916
            ],
            [
              211.0653076171875,
              117.64422607421875,
              0.024773402139544487
            ],
            [
              211.98216247558594,
              118.19966125488281,
              0.4464786946773529
            ],
            [
              190.0131072998047,
              118.66972351074219,
              0.08192723244428635
            ],
            [
              202.9574737548828,
              120.78694152832031,
              0.9716596603393555
            ],
            [
              175.80763244628906,
              142.15716552734375,
              0.9737715125083923
            ],
            [
              212.4232635498047,
              151.62451171875,
              0.9988172650337219
            ],
            [
              175.7313690185547,
              167.82168579101562,
              0.35590171813964844
            ],
            [
              234.72218322753906,
              189.1633758544922,
              0.9940239787101746
            ],
            [
              193.90138244628906,
              183.41732788085938,
              0.16310861706733704
            ],
            [
              258.6708984375,
              203.9674072265625,
              0.9482403993606567
            ],
            [
              192.53060913085938,
              198.0867919921875,
              0.9892897009849548
            ],
            [
              215.8718719482422,
              204.5414276123047,
              0.9976492524147034
            ],
            [
              213.03948974609375,
              225.98915100097656,
              0.983292281627655
            ],
            [
              233.07801818847656,
              236.69915771484375,
              0.9975659847259521
            ],
            [
              215.0065460205078,
              264.4167785644531,
              0.9684734344482422
            ],
            [
              231.05995178222656,
              279.2886047363281,
              0.9919729232788086
            ]
          ],
          "bbox": [
            163.3799591064453,
            91.7373275756836,
            108.01258850097656,
            206.61572265625
          ],
          "bbox_confidence": 0.9263265132904053
        },
        {
          "frame_num": 38,
          "keypoints": [
            [
              235.00181579589844,
              112.82211303710938,
              0.3021753132343292
            ],
            [
              231.3616180419922,
              108.90059661865234,
              0.020916270092129707
            ],
            [
              231.65435791015625,
              109.22266387939453,
              0.433154433965683
            ],
            [
              208.90237426757812,
              111.16206359863281,
              0.09929285943508148
            ],
            [
              223.54586791992188,
              113.89544677734375,
              0.9768075942993164
            ],
            [
              190.73440551757812,
              135.35179138183594,
              0.9863888621330261
            ],
            [
              233.40438842773438,
              142.93896484375,
              0.9992839694023132
            ],
            [
              191.3130340576172,
              160.73272705078125,
              0.39806661009788513
            ],
            [
              251.78355407714844,
              177.23704528808594,
              0.9957322478294373
            ],
            [
              200.96151733398438,
              174.80564880371094,
              0.15518347918987274
            ],
            [
              273.2134094238281,
              185.84939575195312,
              0.956200122833252
            ],
            [
              207.9654083251953,
              189.97938537597656,
              0.994424045085907
            ],
            [
              231.99993896484375,
              195.74559020996094,
              0.9987550973892212
            ],
            [
              231.3981475830078,
              219.42807006835938,
              0.9882709383964539
            ],
            [
              241.1392059326172,
              236.46133422851562,
              0.9985643029212952
            ],
            [
              254.84869384765625,
              246.94253540039062,
              0.9791176319122314
            ],
            [
              231.07333374023438,
              279.9573974609375,
              0.9950470924377441
            ]
          ],
          "bbox": [
            179.86009216308594,
            83.99974822998047,
            107.93937683105469,
            207.18936157226562
          ],
          "bbox_confidence": 0.9212682247161865
        },
        {
          "frame_num": 39,
          "keypoints": [
            [
              253.49183654785156,
              103.57703399658203,
              0.4620390832424164
            ],
            [
              249.89572143554688,
              99.4697265625,
              0.016385393217206
            ],
            [
              249.5591583251953,
              99.8570785522461,
              0.5638103485107422
            ],
            [
              228.06768798828125,
              102.47160339355469,
              0.03238566964864731
            ],
            [
              240.46807861328125,
              104.98809051513672,
              0.9837555885314941
            ],
            [
              211.4761962890625,
              127.30876159667969,
              0.9939980506896973
            ],
            [
              249.06658935546875,
              134.53134155273438,
              0.9994015693664551
            ],
            [
              212.79176330566406,
              153.39544677734375,
              0.6088526248931885
            ],
            [
              265.1163330078125,
              170.0164794921875,
              0.9969488978385925
            ],
            [
              220.61468505859375,
              175.59744262695312,
              0.2867206037044525
            ],
            [
              283.50262451171875,
              185.36709594726562,
              0.9746155738830566
            ],
            [
              224.84266662597656,
              180.32827758789062,
              0.9974881410598755
            ],
            [
              244.47683715820312,
              186.0742950439453,
              0.9991129040718079
            ],
            [
              252.38497924804688,
              212.3848114013672,
              0.99580317735672
            ],
            [
              254.11473083496094,
              229.06143188476562,
              0.9991065859794617
            ],
            [
              268.93646240234375,
              242.0994110107422,
              0.9893044233322144
            ],
            [
              235.35107421875,
              273.4982604980469,
              0.9960327744483948
            ]
          ],
          "bbox": [
            199.7969970703125,
            75.55020904541016,
            98.4326171875,
            210.19879150390625
          ],
          "bbox_confidence": 0.9276314377784729
        },
        {
          "frame_num": 40,
          "keypoints": [
            [
              264.7620849609375,
              96.33946990966797,
              0.6764546036720276
            ],
            [
              264.2494812011719,
              92.05657958984375,
              0.050545718520879745
            ],
            [
              262.2801208496094,
              92.51831817626953,
              0.7877114415168762
            ],
            [
              244.30108642578125,
              91.9530029296875,
              0.026017971336841583
            ],
            [
              252.69566345214844,
              94.18159484863281,
              0.9855048060417175
            ],
            [
              227.7672119140625,
              112.15435028076172,
              0.9762408137321472
            ],
            [
              257.68035888671875,
              121.13977813720703,
              0.9980632662773132
            ],
            [
              226.69834899902344,
              136.74758911132812,
              0.3349064290523529
            ],
            [
              271.74468994140625,
              155.3200225830078,
              0.9084416031837463
            ],
            [
              240.5368194580078,
              148.96331787109375,
              0.1354110985994339
            ],
            [
              283.0812072753906,
              162.08102416992188,
              0.49601900577545166
            ],
            [
              239.7963409423828,
              167.244873046875,
              0.9871310591697693
            ],
            [
              259.08251953125,
              172.88986206054688,
              0.9960963129997253
            ],
            [
              261.44140625,
              200.67266845703125,
              0.989200234413147
            ],
            [
              280.79962158203125,
              205.47084045410156,
              0.9970349073410034
            ],
            [
              265.07464599609375,
              234.9798126220703,
              0.9842496514320374
            ],
            [
              268.90692138671875,
              238.0441131591797,
              0.9935646653175354
            ]
          ],
          "bbox": [
            217.7719268798828,
            68.6360855102539,
            82.08061218261719,
            193.33926391601562
          ],
          "bbox_confidence": 0.8989598751068115
        },
        {
          "frame_num": 41,
          "keypoints": [
            [
              281.87371826171875,
              87.69158172607422,
              0.7567346692085266
            ],
            [
              281.4412536621094,
              83.66673278808594,
              0.05952256917953491
            ],
            [
              279.0005187988281,
              84.39827728271484,
              0.866994321346283
            ],
            [
              260.8900451660156,
              84.76823425292969,
              0.029864540323615074
            ],
            [
              269.7720642089844,
              88.4216537475586,
              0.991327702999115
            ],
            [
              246.291748046875,
              105.39996337890625,
              0.9787054657936096
            ],
            [
              274.588623046875,
              115.66693878173828,
              0.99916672706604
            ],
            [
              243.1852569580078,
              129.32540893554688,
              0.27676305174827576
            ],
            [
              280.2415466308594,
              153.04669189453125,
              0.9877552390098572
            ],
            [
              252.97238159179688,
              157.62997436523438,
              0.1352902501821518
            ],
            [
              295.1183166503906,
              176.2512969970703,
              0.9001385569572449
            ],
            [
              252.29237365722656,
              159.61148071289062,
              0.988132894039154
            ],
            [
              273.3851013183594,
              164.189453125,
              0.9975537657737732
            ],
            [
              267.5143127441406,
              194.67230224609375,
              0.9830774664878845
            ],
            [
              298.8786926269531,
              192.34043884277344,
              0.9974844455718994
            ],
            [
              270.3028869628906,
              236.697265625,
              0.9701868295669556
            ],
            [
              294.90283203125,
              231.17550659179688,
              0.9927022457122803
            ]
          ],
          "bbox": [
            235.40138244628906,
            62.71464538574219,
            77.95304870605469,
            185.97586059570312
          ],
          "bbox_confidence": 0.9036799669265747
        },
        {
          "frame_num": 42,
          "keypoints": [
            [
              299.1225891113281,
              87.195068359375,
              0.5362890958786011
            ],
            [
              297.7369079589844,
              82.59825897216797,
              0.04639676958322525
            ],
            [
              297.8487548828125,
              83.17803955078125,
              0.6458378434181213
            ],
            [
              278.8794860839844,
              81.44343566894531,
              0.051229335367679596
            ],
            [
              288.16180419921875,
              83.61585998535156,
              0.9717884063720703
            ],
            [
              264.2920227050781,
              100.58091735839844,
              0.9569976925849915
            ],
            [
              288.1762390136719,
              107.50856018066406,
              0.997231662273407
            ],
            [
              262.1980285644531,
              124.13419342041016,
              0.2985832393169403
            ],
            [
              298.6563720703125,
              142.00537109375,
              0.9496911764144897
            ],
            [
              278.1929931640625,
              145.91424560546875,
              0.15520572662353516
            ],
            [
              307.36578369140625,
              162.2874755859375,
              0.7025158405303955
            ],
            [
              268.7950439453125,
              154.9964599609375,
              0.9849036931991577
            ],
            [
              287.9172668457031,
              157.80613708496094,
              0.9959840774536133
            ],
            [
              272.678955078125,
              195.24423217773438,
              0.9871616959571838
            ],
            [
              308.6796875,
              190.13473510742188,
              0.9966932535171509
            ],
            [
              272.1686096191406,
              236.0352783203125,
              0.9798663258552551
            ],
            [
              327.65606689453125,
              221.4254608154297,
              0.992647647857666
            ]
          ],
          "bbox": [
            253.1763916015625,
            58.814308166503906,
            85.06954956054688,
            183.96878051757812
          ],
          "bbox_confidence": 0.8853482007980347
        },
        {
          "frame_num": 43,
          "keypoints": [
            [
              318.0962829589844,
              79.26080322265625,
              0.4788937270641327
            ],
            [
              316.3523864746094,
              74.51054382324219,
              0.03571595996618271
            ],
            [
              316.7786865234375,
              75.85604858398438,
              0.6154982447624207
            ],
            [
              298.0242614746094,
              73.929931640625,
              0.06882061809301376
            ],
            [
              309.86346435546875,
              77.97188568115234,
              0.9787940979003906
            ],
            [
              284.3553161621094,
              93.05131530761719,
              0.9798181056976318
            ],
            [
              310.5018615722656,
              103.7357406616211,
              0.9993085861206055
            ],
            [
              278.33782958984375,
              113.72242736816406,
              0.32722654938697815
            ],
            [
              320.1043395996094,
              137.93727111816406,
              0.9944356679916382
            ],
            [
              290.0146179199219,
              137.9662322998047,
              0.16841846704483032
            ],
            [
              334.34674072265625,
              158.31332397460938,
              0.9491012692451477
            ],
            [
              289.37420654296875,
              145.61256408691406,
              0.994439959526062
            ],
            [
              308.5589599609375,
              150.64779663085938,
              0.9988594055175781
            ],
            [
              295.5580139160156,
              180.697265625,
              0.9924319982528687
            ],
            [
              322.67279052734375,
              179.60079956054688,
              0.9987735152244568
            ],
            [
              281.38934326171875,
              219.1930389404297,
              0.9852842688560486
            ],
            [
              326.33221435546875,
              217.5527801513672,
              0.996185839176178
            ]
          ],
          "bbox": [
            270.1827697753906,
            54.35398864746094,
            76.56442260742188,
            180.47434997558594
          ],
          "bbox_confidence": 0.9010462164878845
        },
        {
          "frame_num": 44,
          "keypoints": [
            [
              332.13153076171875,
              74.45995330810547,
              0.7311729192733765
            ],
            [
              331.2464904785156,
              69.96500396728516,
              0.08192866295576096
            ],
            [
              329.9980163574219,
              71.12125396728516,
              0.8121662735939026
            ],
            [
              313.4913024902344,
              68.28219604492188,
              0.05916149169206619
            ],
            [
              321.63836669921875,
              72.2004165649414,
              0.9821258783340454
            ],
            [
              297.5956726074219,
              86.65458679199219,
              0.9887655973434448
            ],
            [
              325.9429016113281,
              97.46673583984375,
              0.9988303780555725
            ],
            [
              290.41162109375,
              105.50594329833984,
              0.5118400454521179
            ],
            [
              337.7498779296875,
              128.20167541503906,
              0.991074800491333
            ],
            [
              300.9005126953125,
              123.36856079101562,
              0.29063165187835693
            ],
            [
              355.30938720703125,
              145.9146728515625,
              0.9505936503410339
            ],
            [
              304.17144775390625,
              136.24195861816406,
              0.9926941394805908
            ],
            [
              322.16436767578125,
              142.02687072753906,
              0.9975530505180359
            ],
            [
              317.0934753417969,
              163.70513916015625,
              0.9860631823539734
            ],
            [
              329.8738098144531,
              172.22866821289062,
              0.9967740178108215
            ],
            [
              314.2054443359375,
              195.5169677734375,
              0.9653891324996948
            ],
            [
              322.758056640625,
              207.266845703125,
              0.9872654676437378
            ]
          ],
          "bbox": [
            285.1441650390625,
            49.396610260009766,
            79.393798828125,
            169.9456024169922
          ],
          "bbox_confidence": 0.9163112640380859
        },
        {
          "frame_num": 45,
          "keypoints": [
            [
              345.6568603515625,
              71.80894470214844,
              0.33746445178985596
            ],
            [
              343.0704345703125,
              67.5625991821289,
              0.030859192833304405
            ],
            [
              343.7236633300781,
              68.34905242919922,
              0.4511135518550873
            ],
            [
              325.8294982910156,
              66.73451232910156,
              0.09262979030609131
            ],
            [
              336.8512878417969,
              69.53424072265625,
              0.9670880436897278
            ],
            [
              309.8820495605469,
              85.31832885742188,
              0.9835819005966187
            ],
            [
              341.6676025390625,
              93.134765625,
              0.9991092085838318
            ],
            [
              304.61737060546875,
              108.61314392089844,
              0.4276134669780731
            ],
            [
              354.5185546875,
              123.95907592773438,
              0.9938763976097107
            ],
            [
              312.4784240722656,
              125.90923309326172,
              0.16534799337387085
            ],
            [
              372.129638671875,
              138.95257568359375,
              0.9335179328918457
            ],
            [
              319.52374267578125,
              132.5696563720703,
              0.9940237402915955
            ],
            [
              335.9073181152344,
              138.44100952148438,
              0.9984839558601379
            ],
            [
              337.585205078125,
              161.31121826171875,
              0.9889854192733765
            ],
            [
              334.78717041015625,
              175.25955200195312,
              0.9979071617126465
            ],
            [
              349.4903869628906,
              186.44418334960938,
              0.978670060634613
            ],
            [
              325.0269470214844,
              211.22244262695312,
              0.9931541681289673
            ]
          ],
          "bbox": [
            299.1575622558594,
            46.48678207397461,
            82.4638671875,
            168.4661102294922
          ],
          "bbox_confidence": 0.9271050691604614
        },
        {
          "frame_num": 46,
          "keypoints": [
            [
              358.168701171875,
              67.6283187866211,
              0.3911330997943878
            ],
            [
              355.8252258300781,
              64.06015014648438,
              0.027471443638205528
            ],
            [
              355.7779541015625,
              64.58941650390625,
              0.49430355429649353
            ],
            [
              340.341796875,
              64.81153869628906,
              0.053938157856464386
            ],
            [
              349.4920349121094,
              67.05555725097656,
              0.9698455333709717
            ],
            [
              326.58319091796875,
              82.47933959960938,
              0.9850354194641113
            ],
            [
              356.0594787597656,
              89.62523651123047,
              0.9989402890205383
            ],
            [
              321.8774108886719,
              98.28898620605469,
              0.4858013689517975
            ],
            [
              365.30810546875,
              119.57234191894531,
              0.9921160340309143
            ],
            [
              330.474853515625,
              107.66108703613281,
              0.19553647935390472
            ],
            [
              381.1005554199219,
              139.5035400390625,
              0.9227972626686096
            ],
            [
              335.7693786621094,
              128.97079467773438,
              0.9959218502044678
            ],
            [
              350.4468688964844,
              133.87753295898438,
              0.9988248944282532
            ],
            [
              350.15478515625,
              156.750244140625,
              0.9926884174346924
            ],
            [
              348.3190002441406,
              169.26417541503906,
              0.9983483552932739
            ],
            [
              366.17803955078125,
              179.19850158691406,
              0.9852389097213745
            ],
            [
              329.32769775390625,
              204.71926879882812,
              0.9946304559707642
            ]
          ],
          "bbox": [
            314.6752624511719,
            44.67254638671875,
            78.543701171875,
            164.08535766601562
          ],
          "bbox_confidence": 0.9081831574440002
        },
        {
          "frame_num": 47,
          "keypoints": [
            [
              370.1607666015625,
              65.02467346191406,
              0.3947906196117401
            ],
            [
              368.8198547363281,
              61.254207611083984,
              0.0418178029358387
            ],
            [
              368.67816162109375,
              61.9792366027832,
              0.5122857689857483
            ],
            [
              353.07196044921875,
              60.51729965209961,
              0.08824535459280014
            ],
            [
              362.0780029296875,
              62.59223937988281,
              0.9609571099281311
            ],
            [
              340.65191650390625,
              77.25634765625,
              0.9716401696205139
            ],
            [
              366.4807434082031,
              82.79328918457031,
              0.9988043308258057
            ],
            [
              338.9326171875,
              97.7838134765625,
              0.35676079988479614
            ],
            [
              374.6817932128906,
              112.21634674072266,
              0.9921757578849792
            ],
            [
              348.49859619140625,
              115.85466766357422,
              0.17750760912895203
            ],
            [
              385.0235290527344,
              133.0189971923828,
              0.934782862663269
            ],
            [
              347.9684143066406,
              121.91503143310547,
              0.9925668239593506
            ],
            [
              363.9595031738281,
              125.20269775390625,
              0.9984083771705627
            ],
            [
              363.4560852050781,
              153.18370056152344,
              0.9895855784416199
            ],
            [
              371.66748046875,
              155.4080810546875,
              0.9983172416687012
            ],
            [
              362.97259521484375,
              180.94065856933594,
              0.981827437877655
            ],
            [
              359.01470947265625,
              185.96429443359375,
              0.9952644109725952
            ]
          ],
          "bbox": [
            331.51708984375,
            41.5140380859375,
            65.37094116210938,
            157.79637145996094
          ],
          "bbox_confidence": 0.9033900499343872
        },
        {
          "frame_num": 48,
          "keypoints": [
            [
              385.20855712890625,
              59.562889099121094,
              0.44980496168136597
            ],
            [
              385.6692810058594,
              56.47320556640625,
              0.04947114735841751
            ],
            [
              383.5981750488281,
              56.405513763427734,
              0.6276429891586304
            ],
            [
              368.49603271484375,
              56.255367279052734,
              0.08971139043569565
            ],
            [
              376.5287170410156,
              57.75013732910156,
              0.9750022292137146
            ],
            [
              354.289794921875,
              72.98780822753906,
              0.9475575089454651
            ],
            [
              378.363525390625,
              77.22466278076172,
              0.9986948370933533
            ],
            [
              354.000732421875,
              93.23616790771484,
              0.21545223891735077
            ],
            [
              384.8625793457031,
              106.78987121582031,
              0.9882441759109497
            ],
            [
              363.886474609375,
              112.27422332763672,
              0.11305708438158035
            ],
            [
              395.4083557128906,
              131.00621032714844,
              0.896210789680481
            ],
            [
              358.54815673828125,
              118.94487762451172,
              0.9859786629676819
            ],
            [
              376.4026184082031,
              120.34618377685547,
              0.9979362487792969
            ],
            [
              365.753662109375,
              150.01036071777344,
              0.9813809394836426
            ],
            [
              393.50738525390625,
              146.46998596191406,
              0.9979771971702576
            ],
            [
              366.77227783203125,
              183.08396911621094,
              0.9766430854797363
            ],
            [
              383.8637390136719,
              178.00711059570312,
              0.9956325888633728
            ]
          ],
          "bbox": [
            347.15936279296875,
            38.53010177612305,
            58.12261962890625,
            153.80776977539062
          ],
          "bbox_confidence": 0.8934779167175293
        },
        {
          "frame_num": 49,
          "keypoints": [
            [
              397.9137268066406,
              61.012996673583984,
              0.8487957715988159
            ],
            [
              397.68414306640625,
              57.08811569213867,
              0.10877314954996109
            ],
            [
              396.1843566894531,
              57.70387268066406,
              0.9142687916755676
            ],
            [
              384.1231994628906,
              55.53132629394531,
              0.02382144145667553
            ],
            [
              388.3916320800781,
              57.58740234375,
              0.9854561686515808
            ],
            [
              370.7756652832031,
              70.1355209350586,
              0.9672329425811768
            ],
            [
              389.9404296875,
              77.58833312988281,
              0.9986598491668701
            ],
            [
              371.19305419921875,
              84.13817596435547,
              0.30195125937461853
            ],
            [
              396.1685791015625,
              105.81883239746094,
              0.9857029318809509
            ],
            [
              389.72369384765625,
              88.20367431640625,
              0.2640460133552551
            ],
            [
              406.135986328125,
              125.03437042236328,
              0.9235983490943909
            ],
            [
              373.3369445800781,
              115.79356384277344,
              0.9891461133956909
            ],
            [
              389.01531982421875,
              118.49365234375,
              0.9976934790611267
            ],
            [
              372.4131774902344,
              148.31712341308594,
              0.9906909465789795
            ],
            [
              401.11669921875,
              144.91885375976562,
              0.9982831478118896
            ],
            [
              367.04608154296875,
              182.53285217285156,
              0.9858303666114807
            ],
            [
              413.1671447753906,
              172.49432373046875,
              0.9958725571632385
            ]
          ],
          "bbox": [
            360.669677734375,
            39.23747253417969,
            64.58901977539062,
            151.24234008789062
          ],
          "bbox_confidence": 0.8833842277526855
        },
        {
          "frame_num": 50,
          "keypoints": [
            [
              414.9083557128906,
              58.47779846191406,
              0.16063997149467468
            ],
            [
              413.22564697265625,
              54.81013870239258,
              0.01699010282754898
            ],
            [
              414.118896484375,
              55.62076187133789,
              0.19845625758171082
            ],
            [
              398.7325744628906,
              53.887290954589844,
              0.1310546100139618
            ],
            [
              408.8201599121094,
              56.4105339050293,
              0.9334585070610046
            ],
            [
              387.504150390625,
              70.05197143554688,
              0.9817813634872437
            ],
            [
              408.5909423828125,
              75.77762603759766,
              0.9989389777183533
            ],
            [
              380.776123046875,
              85.53620147705078,
              0.45308125019073486
            ],
            [
              413.3515930175781,
              102.37715148925781,
              0.9943612813949585
            ],
            [
              389.5016784667969,
              101.23561096191406,
              0.19437538087368011
            ],
            [
              421.1579284667969,
              122.48553466796875,
              0.9450292587280273
            ],
            [
              388.1195068359375,
              113.03545379638672,
              0.9972714781761169
            ],
            [
              404.38983154296875,
              115.66600036621094,
              0.999268114566803
            ],
            [
              386.8958740234375,
              143.97698974609375,
              0.9958088397979736
            ],
            [
              417.464599609375,
              142.4434356689453,
              0.9990924596786499
            ],
            [
              373.57257080078125,
              173.61141967773438,
              0.9910449981689453
            ],
            [
              419.1297302246094,
              173.48220825195312,
              0.9971690773963928
            ]
          ],
          "bbox": [
            369.00970458984375,
            38.102352142333984,
            65.71044921875,
            146.74407958984375
          ],
          "bbox_confidence": 0.8876778483390808
        },
        {
          "frame_num": 51,
          "keypoints": [
            [
              426.4316711425781,
              57.49449157714844,
              0.01782645843923092
            ],
            [
              424.95269775390625,
              53.80967712402344,
              0.00549660250544548
            ],
            [
              426.0064697265625,
              55.06416702270508,
              0.016552502289414406
            ],
            [
              410.7193908691406,
              51.3271598815918,
              0.38096171617507935
            ],
            [
              423.2156982421875,
              55.400203704833984,
              0.7268769145011902
            ],
            [
              399.4110107421875,
              65.27958679199219,
              0.9860785603523254
            ],
            [
              422.6798400878906,
              76.69983673095703,
              0.9977779984474182
            ],
            [
              392.0352478027344,
              76.2035903930664,
              0.5809417963027954
            ],
            [
              429.6245422363281,
              103.47561645507812,
              0.9908118844032288
            ],
            [
              401.66009521484375,
              91.57840728759766,
              0.17296579480171204
            ],
            [
              441.618896484375,
              118.92001342773438,
              0.8938739895820618
            ],
            [
              402.701904296875,
              106.83814239501953,
              0.9974453449249268
            ],
            [
              418.5088195800781,
              112.9028091430664,
              0.9989369511604309
            ],
            [
              408.2538146972656,
              133.24783325195312,
              0.9933494925498962
            ],
            [
              424.2704772949219,
              139.20252990722656,
              0.9980581402778625
            ],
            [
              395.67095947265625,
              160.17324829101562,
              0.9858623147010803
            ],
            [
              418.2155456542969,
              172.09027099609375,
              0.994400680065155
            ]
          ],
          "bbox": [
            384.55322265625,
            36.45658493041992,
            64.05435180664062,
            142.8157958984375
          ],
          "bbox_confidence": 0.9002801775932312
        },
        {
          "frame_num": 52,
          "keypoints": [
            [
              436.42822265625,
              56.231380462646484,
              0.009449009783565998
            ],
            [
              434.7364807128906,
              52.600284576416016,
              0.0043035889975726604
            ],
            [
              436.2275390625,
              54.012062072753906,
              0.00925375521183014
            ],
            [
              421.9543762207031,
              49.50694274902344,
              0.5462369322776794
            ],
            [
              434.24951171875,
              54.47150421142578,
              0.7306907176971436
            ],
            [
              408.2801818847656,
              63.296119689941406,
              0.9905258417129517
            ],
            [
              432.0982360839844,
              74.91300201416016,
              0.9987308382987976
            ],
            [
              399.734619140625,
              75.30784606933594,
              0.5966275334358215
            ],
            [
              439.6108703613281,
              100.76078796386719,
              0.9950049519538879
            ],
            [
              410.6263732910156,
              88.47500610351562,
              0.12956446409225464
            ],
            [
              454.9319763183594,
              114.34259033203125,
              0.9079377055168152
            ],
            [
              412.2364196777344,
              105.48291778564453,
              0.9968000650405884
            ],
            [
              426.1722717285156,
              112.06765747070312,
              0.9987146854400635
            ],
            [
              425.0187072753906,
              129.7537384033203,
              0.9866543412208557
            ],
            [
              428.82568359375,
              135.60475158691406,
              0.9963520765304565
            ],
            [
              425.5306701660156,
              156.7784881591797,
              0.9715365767478943
            ],
            [
              421.1499938964844,
              167.11737060546875,
              0.9895413517951965
            ]
          ],
          "bbox": [
            396.87310791015625,
            35.49775314331055,
            67.02117919921875,
            141.27011108398438
          ],
          "bbox_confidence": 0.9088088274002075
        },
        {
          "frame_num": 53,
          "keypoints": [
            [
              446.280517578125,
              56.4069938659668,
              0.015981025993824005
            ],
            [
              444.81817626953125,
              52.64159393310547,
              0.005797107238322496
            ],
            [
              445.3717956542969,
              53.98680877685547,
              0.019824611023068428
            ],
            [
              429.0255126953125,
              50.307247161865234,
              0.4163515269756317
            ],
            [
              442.63311767578125,
              55.509857177734375,
              0.7472214102745056
            ],
            [
              417.4007568359375,
              64.00900268554688,
              0.97003573179245
            ],
            [
              439.5833740234375,
              74.88784790039062,
              0.9983627200126648
            ],
            [
              416.7958068847656,
              80.38882446289062,
              0.3789314329624176
            ],
            [
              445.41595458984375,
              101.33067321777344,
              0.9951938986778259
            ],
            [
              426.49951171875,
              100.10809326171875,
              0.1119382306933403
            ],
            [
              459.3460388183594,
              115.85550689697266,
              0.9288421869277954
            ],
            [
              414.3108825683594,
              103.51828002929688,
              0.9935892820358276
            ],
            [
              426.7008056640625,
              109.47196197509766,
              0.9985176920890808
            ],
            [
              434.47027587890625,
              125.64654541015625,
              0.9818359613418579
            ],
            [
              435.0453796386719,
              135.88885498046875,
              0.9973995685577393
            ],
            [
              439.5784912109375,
              152.02011108398438,
              0.97237229347229
            ],
            [
              421.0130310058594,
              169.524658203125,
              0.9933731555938721
            ]
          ],
          "bbox": [
            404.7768859863281,
            35.008575439453125,
            67.728759765625,
            141.85972595214844
          ],
          "bbox_confidence": 0.8942816853523254
        },
        {
          "frame_num": 54,
          "keypoints": [
            [
              448.45904541015625,
              54.266963958740234,
              0.12111255526542664
            ],
            [
              448.59222412109375,
              50.84840393066406,
              0.03176392614841461
            ],
            [
              447.9415283203125,
              51.70307540893555,
              0.15769310295581818
            ],
            [
              436.30670166015625,
              48.73609161376953,
              0.19519975781440735
            ],
            [
              445.16680908203125,
              52.138736724853516,
              0.7639025449752808
            ],
            [
              425.9250183105469,
              60.52903366088867,
              0.8915150165557861
            ],
            [
              441.6915588378906,
              70.79895782470703,
              0.9937124848365784
            ],
            [
              428.4827575683594,
              76.80159759521484,
              0.26434600353240967
            ],
            [
              448.0213317871094,
              98.07200622558594,
              0.9843596816062927
            ],
            [
              439.54254150390625,
              98.82443237304688,
              0.16710522770881653
            ],
            [
              457.57763671875,
              115.87499237060547,
              0.9154682755470276
            ],
            [
              426.298583984375,
              100.36502838134766,
              0.9723915457725525
            ],
            [
              436.5475158691406,
              105.70507049560547,
              0.9939911961555481
            ],
            [
              442.36334228515625,
              124.91077423095703,
              0.9511241912841797
            ],
            [
              448.37640380859375,
              130.80540466308594,
              0.9927842617034912
            ],
            [
              435.991943359375,
              151.90440368652344,
              0.9288603067398071
            ],
            [
              434.8196716308594,
              159.61129760742188,
              0.9825890064239502
            ]
          ],
          "bbox": [
            416.020263671875,
            34.54830551147461,
            55.3345947265625,
            137.5825958251953
          ],
          "bbox_confidence": 0.7934250235557556
        },
        {
          "frame_num": 55,
          "keypoints": [
            [
              455.656494140625,
              55.36978530883789,
              0.15510596334934235
            ],
            [
              456.5948486328125,
              52.05254364013672,
              0.03881501778960228
            ],
            [
              455.3495178222656,
              52.67281723022461,
              0.21118491888046265
            ],
            [
              445.8311767578125,
              48.82707214355469,
              0.1187201738357544
            ],
            [
              450.8796691894531,
              51.4072380065918,
              0.7454314827919006
            ],
            [
              437.1550598144531,
              60.96769714355469,
              0.782602846622467
            ],
            [
              444.61236572265625,
              68.16498565673828,
              0.9918769598007202
            ],
            [
              448.5817565917969,
              83.566162109375,
              0.17506836354732513
            ],
            [
              451.01336669921875,
              95.3100357055664,
              0.9750824570655823
            ],
            [
              457.5447998046875,
              108.29301452636719,
              0.14691807329654694
            ],
            [
              457.797607421875,
              115.58853149414062,
              0.8733698129653931
            ],
            [
              436.7867126464844,
              101.30738067626953,
              0.9623788595199585
            ],
            [
              443.60906982421875,
              105.30513763427734,
              0.9936641454696655
            ],
            [
              442.4721984863281,
              128.31980895996094,
              0.9594529867172241
            ],
            [
              451.014404296875,
              130.65089416503906,
              0.9945937991142273
            ],
            [
              438.6914367675781,
              158.03041076660156,
              0.9529281258583069
            ],
            [
              443.5575866699219,
              159.7265625,
              0.9896580576896667
            ]
          ],
          "bbox": [
            426.0209045410156,
            35.720699310302734,
            43.602142333984375,
            134.49832153320312
          ],
          "bbox_confidence": 0.7784233689308167
        },
        {
          "frame_num": 56,
          "keypoints": [
            [
              465.3447265625,
              59.34278869628906,
              0.10497836023569107
            ],
            [
              465.2625732421875,
              55.74448013305664,
              0.024944614619016647
            ],
            [
              465.3165283203125,
              56.985164642333984,
              0.14750421047210693
            ],
            [
              451.26983642578125,
              52.797767639160156,
              0.17068204283714294
            ],
            [
              461.01837158203125,
              57.239097595214844,
              0.8136899471282959
            ],
            [
              441.0606689453125,
              63.67825698852539,
              0.8921263813972473
            ],
            [
              455.78607177734375,
              75.28939819335938,
              0.9962499737739563
            ],
            [
              445.2186584472656,
              78.77628326416016,
              0.22227998077869415
            ],
            [
              458.4229431152344,
              100.91878509521484,
              0.987275242805481
            ],
            [
              459.0351867675781,
              96.98939514160156,
              0.13435238599777222
            ],
            [
              467.33721923828125,
              117.25171661376953,
              0.901878297328949
            ],
            [
              438.0822448730469,
              102.45325469970703,
              0.9814574122428894
            ],
            [
              449.2398681640625,
              108.30790710449219,
              0.9966585636138916
            ],
            [
              448.0892028808594,
              129.20291137695312,
              0.9719617366790771
            ],
            [
              458.25665283203125,
              132.83163452148438,
              0.9961407780647278
            ],
            [
              439.6458435058594,
              157.70433044433594,
              0.9614278674125671
            ],
            [
              444.0224304199219,
              158.56198120117188,
              0.9914005398750305
            ]
          ],
          "bbox": [
            431.7806396484375,
            37.95637893676758,
            44.60870361328125,
            131.35366821289062
          ],
          "bbox_confidence": 0.8227790594100952
        },
        {
          "frame_num": 57,
          "keypoints": [
            [
              469.41204833984375,
              70.47804260253906,
              0.02567869797348976
            ],
            [
              468.55548095703125,
              66.44669342041016,
              0.010289432480931282
            ],
            [
              469.20196533203125,
              68.20328521728516,
              0.02822365239262581
            ],
            [
              455.2781677246094,
              60.87998580932617,
              0.3125839829444885
            ],
            [
              465.94403076171875,
              66.87496948242188,
              0.6044608950614929
            ],
            [
              444.5569152832031,
              69.94230651855469,
              0.893804669380188
            ],
            [
              460.216796875,
              85.21443176269531,
              0.9951269626617432
            ],
            [
              451.3882141113281,
              85.12876892089844,
              0.2557392418384552
            ],
            [
              471.9276123046875,
              110.23099517822266,
              0.9882299900054932
            ],
            [
              465.8913879394531,
              107.91053009033203,
              0.1245560497045517
            ],
            [
              485.9850769042969,
              126.83023071289062,
              0.8950997591018677
            ],
            [
              444.98370361328125,
              110.37865447998047,
              0.9853675365447998
            ],
            [
              456.7389221191406,
              119.23135375976562,
              0.9970685839653015
            ],
            [
              452.729248046875,
              126.97502136230469,
              0.9683383703231812
            ],
            [
              468.1844787597656,
              139.76272583007812,
              0.995500385761261
            ],
            [
              436.456298828125,
              144.9277801513672,
              0.9617863297462463
            ],
            [
              449.09332275390625,
              159.3829345703125,
              0.9909998774528503
            ]
          ],
          "bbox": [
            432.5877990722656,
            44.149654388427734,
            59.804595947265625,
            123.21832275390625
          ],
          "bbox_confidence": 0.8404884934425354
        },
        {
          "frame_num": 58,
          "keypoints": [
            [
              477.62420654296875,
              102.89749145507812,
              0.013321229256689548
            ],
            [
              476.9200744628906,
              98.88396453857422,
              0.005911519750952721
            ],
            [
              477.8105773925781,
              101.41727447509766,
              0.015059473924338818
            ],
            [
              463.2276611328125,
              93.57130432128906,
              0.4751451015472412
            ],
            [
              475.68243408203125,
              102.18866729736328,
              0.6813495755195618
            ],
            [
              448.95843505859375,
              101.55390167236328,
              0.952355146408081
            ],
            [
              474.0107116699219,
              118.85317993164062,
              0.9935759902000427
            ],
            [
              447.0872497558594,
              105.85888671875,
              0.4059763550758362
            ],
            [
              490.5263671875,
              137.4384765625,
              0.9906097054481506
            ],
            [
              458.9505615234375,
              112.8058090209961,
              0.09461437165737152
            ],
            [
              511.437255859375,
              136.90843200683594,
              0.87614506483078
            ],
            [
              441.1962890625,
              145.8635711669922,
              0.9278889894485474
            ],
            [
              458.3702697753906,
              154.02325439453125,
              0.9713719487190247
            ],
            [
              456.6290283203125,
              144.5755615234375,
              0.22877448797225952
            ],
            [
              474.01434326171875,
              150.60446166992188,
              0.551355242729187
            ],
            [
              447.63494873046875,
              155.42178344726562,
              0.07090623676776886
            ],
            [
              462.36663818359375,
              160.2366485595703,
              0.1856028139591217
            ]
          ],
          "bbox": [
            436.40521240234375,
            70.80390930175781,
            78.75067138671875,
            94.04104614257812
          ],
          "bbox_confidence": 0.7339562177658081
        },
        {
          "frame_num": 59,
          "keypoints": null,
          "bbox": null,
          "bbox_confidence": null
        },
        {
          "frame_num": 60,
          "keypoints": null,
          "bbox": null,
          "bbox_confidence": null
        },
        {
          "frame_num": 61,
          "keypoints": null,
          "bbox": null,
          "bbox_confidence": null
        },
        {
          "frame_num": 62,
          "keypoints": null,
          "bbox": null,
          "bbox_confidence": null
        },
        {
          "frame_num": 63,
          "keypoints": null,
          "bbox": null,
          "bbox_confidence": null
        },
        {
          "frame_num": 64,
          "keypoints": null,
          "bbox": null,
          "bbox_confidence": null
        },
        {
          "frame_num": 65,
          "keypoints": null,
          "bbox": null,
          "bbox_confidence": null
        },
        {
          "frame_num": 66,
          "keypoints": null,
          "bbox": null,
          "bbox_confidence": null
        },
        {
          "frame_num": 67,
          "keypoints": null,
          "bbox": null,
          "bbox_confidence": null
        },
        {
          "frame_num": 68,
          "keypoints": null,
          "bbox": null,
          "bbox_confidence": null
        },
        {
          "frame_num": 69,
          "keypoints": null,
          "bbox": null,
          "bbox_confidence": null
        },
        {
          "frame_num": 70,
          "keypoints": null,
          "bbox": null,
          "bbox_confidence": null
        },
        {
          "frame_num": 71,
          "keypoints": null,
          "bbox": null,
          "bbox_confidence": null
        },
        {
          "frame_num": 72,
          "keypoints": null,
          "bbox": null,
          "bbox_confidence": null
        },
        {
          "frame_num": 73,
          "keypoints": null,
          "bbox": null,
          "bbox_confidence": null
        },
        {
          "frame_num": 74,
          "keypoints": null,
          "bbox": null,
          "bbox_confidence": null
        },
        {
          "frame_num": 75,
          "keypoints": null,
          "bbox": null,
          "bbox_confidence": null
        },
        {
          "frame_num": 76,
          "keypoints": null,
          "bbox": null,
          "bbox_confidence": null
        },
        {
          "frame_num": 77,
          "keypoints": null,
          "bbox": null,
          "bbox_confidence": null
        },
        {
          "frame_num": 78,
          "keypoints": null,
          "bbox": null,
          "bbox_confidence": null
        },
        {
          "frame_num": 79,
          "keypoints": null,
          "bbox": null,
          "bbox_confidence": null
        },
        {
          "frame_num": 80,
          "keypoints": null,
          "bbox": null,
          "bbox_confidence": null
        },
        {
          "frame_num": 81,
          "keypoints": null,
          "bbox": null,
          "bbox_confidence": null
        },
        {
          "frame_num": 82,
          "keypoints": null,
          "bbox": null,
          "bbox_confidence": null
        },
        {
          "frame_num": 83,
          "keypoints": null,
          "bbox": null,
          "bbox_confidence": null
        },
        {
          "frame_num": 84,
          "keypoints": null,
          "bbox": null,
          "bbox_confidence": null
        },
        {
          "frame_num": 85,
          "keypoints": null,
          "bbox": null,
          "bbox_confidence": null
        },
        {
          "frame_num": 86,
          "keypoints": null,
          "bbox": null,
          "bbox_confidence": null
        },
        {
          "frame_num": 87,
          "keypoints": null,
          "bbox": null,
          "bbox_confidence": null
        },
        {
          "frame_num": 88,
          "keypoints": null,
          "bbox": null,
          "bbox_confidence": null
        },
        {
          "frame_num": 89,
          "keypoints": null,
          "bbox": null,
          "bbox_confidence": null
        },
        {
          "frame_num": 90,
          "keypoints": null,
          "bbox": null,
          "bbox_confidence": null
        },
        {
          "frame_num": 91,
          "keypoints": null,
          "bbox": null,
          "bbox_confidence": null
        },
        {
          "frame_num": 92,
          "keypoints": null,
          "bbox": null,
          "bbox_confidence": null
        },
        {
          "frame_num": 93,
          "keypoints": null,
          "bbox": null,
          "bbox_confidence": null
        },
        {
          "frame_num": 94,
          "keypoints": null,
          "bbox": null,
          "bbox_confidence": null
        },
        {
          "frame_num": 95,
          "keypoints": null,
          "bbox": null,
          "bbox_confidence": null
        },
        {
          "frame_num": 96,
          "keypoints": null,
          "bbox": null,
          "bbox_confidence": null
        },
        {
          "frame_num": 97,
          "keypoints": null,
          "bbox": null,
          "bbox_confidence": null
        },
        {
          "frame_num": 98,
          "keypoints": null,
          "bbox": null,
          "bbox_confidence": null
        },
        {
          "frame_num": 99,
          "keypoints": null,
          "bbox": null,
          "bbox_confidence": null
        },
        {
          "frame_num": 100,
          "keypoints": null,
          "bbox": null,
          "bbox_confidence": null
        },
        {
          "frame_num": 101,
          "keypoints": null,
          "bbox": null,
          "bbox_confidence": null
        },
        {
          "frame_num": 102,
          "keypoints": null,
          "bbox": null,
          "bbox_confidence": null
        },
        {
          "frame_num": 103,
          "keypoints": null,
          "bbox": null,
          "bbox_confidence": null
        },
        {
          "frame_num": 104,
          "keypoints": null,
          "bbox": null,
          "bbox_confidence": null
        },
        {
          "frame_num": 105,
          "keypoints": null,
          "bbox": null,
          "bbox_confidence": null
        },
        {
          "frame_num": 106,
          "keypoints": null,
          "bbox": null,
          "bbox_confidence": null
        },
        {
          "frame_num": 107,
          "keypoints": null,
          "bbox": null,
          "bbox_confidence": null
        },
        {
          "frame_num": 108,
          "keypoints": null,
          "bbox": null,
          "bbox_confidence": null
        },
        {
          "frame_num": 109,
          "keypoints": null,
          "bbox": null,
          "bbox_confidence": null
        },
        {
          "frame_num": 110,
          "keypoints": null,
          "bbox": null,
          "bbox_confidence": null
        },
        {
          "frame_num": 111,
          "keypoints": null,
          "bbox": null,
          "bbox_confidence": null
        },
        {
          "frame_num": 112,
          "keypoints": null,
          "bbox": null,
          "bbox_confidence": null
        },
        {
          "frame_num": 113,
          "keypoints": null,
          "bbox": null,
          "bbox_confidence": null
        },
        {
          "frame_num": 114,
          "keypoints": null,
          "bbox": null,
          "bbox_confidence": null
        },
        {
          "frame_num": 115,
          "keypoints": null,
          "bbox": null,
          "bbox_confidence": null
        },
        {
          "frame_num": 116,
          "keypoints": null,
          "bbox": null,
          "bbox_confidence": null
        },
        {
          "frame_num": 117,
          "keypoints": null,
          "bbox": null,
          "bbox_confidence": null
        },
        {
          "frame_num": 118,
          "keypoints": null,
          "bbox": null,
          "bbox_confidence": null
        },
        {
          "frame_num": 119,
          "keypoints": null,
          "bbox": null,
          "bbox_confidence": null
        },
        {
          "frame_num": 120,
          "keypoints": null,
          "bbox": null,
          "bbox_confidence": null
        },
        {
          "frame_num": 121,
          "keypoints": null,
          "bbox": null,
          "bbox_confidence": null
        },
        {
          "frame_num": 122,
          "keypoints": null,
          "bbox": null,
          "bbox_confidence": null
        },
        {
          "frame_num": 123,
          "keypoints": null,
          "bbox": null,
          "bbox_confidence": null
        },
        {
          "frame_num": 124,
          "keypoints": null,
          "bbox": null,
          "bbox_confidence": null
        },
        {
          "frame_num": 125,
          "keypoints": null,
          "bbox": null,
          "bbox_confidence": null
        }
      ],
      "action_labels": [
        {
          "start_frame": 29,
          "end_frame": 47,
          "label": "normal",
          "fall_direction": null,
          "general_action": "walking"
        },
        {
          "start_frame": 56,
          "end_frame": 71,
          "label": "fall",
          "fall_direction": "fall_back",
          "general_action": null
        }
      ]
    }
  ]
}